fullykiosk/__init__.py
fullykiosk/exceptions.py
python_fullykiosk-0.0.14.dist-info/LICENSE
python_fullykiosk-0.0.14.dist-info/METADATA
python_fullykiosk-0.0.14.dist-info/WHEEL
python_fullykiosk-0.0.14.dist-info/top_level.txt
python_fullykiosk-0.0.14.dist-info/RECORD
